pysnmp/__init__.py
pysnmp/cache.py
pysnmp/debug.py
pysnmp/error.py
pysnmp/nextid.py
pysnmp/carrier/__init__.py
pysnmp/carrier/base.py
pysnmp/carrier/error.py
pysnmp/carrier/sockfix.py
pysnmp/carrier/sockmsg.py
pysnmp/carrier/asyncio/__init__.py
pysnmp/carrier/asyncio/base.py
pysnmp/carrier/asyncio/dispatch.py
pysnmp/carrier/asyncio/dgram/__init__.py
pysnmp/carrier/asyncio/dgram/base.py
pysnmp/carrier/asyncio/dgram/udp.py
pysnmp/carrier/asyncio/dgram/udp6.py
pysnmp/carrier/asyncore/__init__.py
pysnmp/carrier/asyncore/base.py
pysnmp/carrier/asyncore/dispatch.py
pysnmp/carrier/asyncore/dgram/__init__.py
pysnmp/carrier/asyncore/dgram/base.py
pysnmp/carrier/asyncore/dgram/udp.py
pysnmp/carrier/asyncore/dgram/udp6.py
pysnmp/carrier/asyncore/dgram/unix.py
pysnmp/carrier/asynsock/__init__.py
pysnmp/carrier/asynsock/dispatch.py
pysnmp/carrier/asynsock/dgram/__init__.py
pysnmp/carrier/asynsock/dgram/udp.py
pysnmp/carrier/asynsock/dgram/udp6.py
pysnmp/carrier/asynsock/dgram/unix.py
pysnmp/carrier/twisted/__init__.py
pysnmp/carrier/twisted/base.py
pysnmp/carrier/twisted/dispatch.py
pysnmp/carrier/twisted/dgram/__init__.py
pysnmp/carrier/twisted/dgram/base.py
pysnmp/carrier/twisted/dgram/udp.py
pysnmp/carrier/twisted/dgram/unix.py
pysnmp/entity/__init__.py
pysnmp/entity/config.py
pysnmp/entity/engine.py
pysnmp/entity/observer.py
pysnmp/entity/rfc3413/__init__.py
pysnmp/entity/rfc3413/cmdgen.py
pysnmp/entity/rfc3413/cmdrsp.py
pysnmp/entity/rfc3413/config.py
pysnmp/entity/rfc3413/context.py
pysnmp/entity/rfc3413/mibvar.py
pysnmp/entity/rfc3413/ntforg.py
pysnmp/entity/rfc3413/ntfrcv.py
pysnmp/entity/rfc3413/oneliner/__init__.py
pysnmp/entity/rfc3413/oneliner/cmdgen.py
pysnmp/entity/rfc3413/oneliner/ntforg.py
pysnmp/hlapi/__init__.py
pysnmp/hlapi/auth.py
pysnmp/hlapi/context.py
pysnmp/hlapi/lcd.py
pysnmp/hlapi/transport.py
pysnmp/hlapi/varbinds.py
pysnmp/hlapi/asyncio/__init__.py
pysnmp/hlapi/asyncio/cmdgen.py
pysnmp/hlapi/asyncio/ntforg.py
pysnmp/hlapi/asyncio/transport.py
bp_pysnmp-4.4.3.dist-info/LICENSE.txt
bp_pysnmp-4.4.3.dist-info/METADATA
bp_pysnmp-4.4.3.dist-info/WHEEL
bp_pysnmp-4.4.3.dist-info/top_level.txt
bp_pysnmp-4.4.3.dist-info/zip-safe
bp_pysnmp-4.4.3.dist-info/RECORD
